skykatana/__init__.py
skykatana/skykatana.py
skykatana-0.2.2.dist-info/licenses/LICENSE
skykatana-0.2.2.dist-info/METADATA
skykatana-0.2.2.dist-info/WHEEL
skykatana-0.2.2.dist-info/top_level.txt
skykatana-0.2.2.dist-info/RECORD
