Metadata-Version: 2.4
Name: skykatana
Version: 0.2.2
Summary: Tookit to create sky masks in a pipeline way
Author-email: "Emilio Donoso, ICATE-Conicet" <emiliodon@gmail.com>
License: MIT License
Project-URL: Homepage, https://github.com/samotracio/skykatana
Project-URL: Documentation, https://skykatana.readthedocs.io/en/latest/
Project-URL: Repository, https://github.com/samotracio/skykatana
Keywords: Astronomy,Surveys,Sky Masks
Classifier: Development Status :: 3 - Alpha
Classifier: Operating System :: OS Independent
Classifier: License :: OSI Approved :: MIT License
Classifier: Programming Language :: Python :: 3
Requires-Python: >=3.10
License-File: LICENSE
Requires-Dist: lsdb
Requires-Dist: healsparse
Requires-Dist: tqdm
Requires-Dist: healpy
Requires-Dist: fitsio
Requires-Dist: pillow
Requires-Dist: ipyaladin
Requires-Dist: reproject
Dynamic: license-file
